AUTHORS
COPYING
ChangeLog
README
THANKS
TODO
bjamcompiler.py
bjamdumpmodule.cpp
config_example_linux.py
config_example_win32.py
ez_setup.py
setup.cfg
setup.py
pyopencv/__init__.py
pyopencv/config.py
pyopencv/core.py
pyopencv/interfaces.py
pyopencv.egg-info/PKG-INFO
pyopencv.egg-info/SOURCES.txt
pyopencv.egg-info/dependency_links.txt
pyopencv.egg-info/top_level.txt
pyopencv/pyopencvext/AutotunedIndexParams.pypp.cpp
pyopencv/pyopencvext/AutotunedIndexParams.pypp.hpp
pyopencv/pyopencvext/BackgroundSubtractor.pypp.cpp
pyopencv/pyopencvext/BackgroundSubtractor.pypp.hpp
pyopencv/pyopencvext/BackgroundSubtractorMOG.pypp.cpp
pyopencv/pyopencvext/BackgroundSubtractorMOG.pypp.hpp
pyopencv/pyopencvext/BaseColumnFilter.pypp.cpp
pyopencv/pyopencvext/BaseColumnFilter.pypp.hpp
pyopencv/pyopencvext/BaseFilter.pypp.cpp
pyopencv/pyopencvext/BaseFilter.pypp.hpp
pyopencv/pyopencvext/BaseRowFilter.pypp.cpp
pyopencv/pyopencvext/BaseRowFilter.pypp.hpp
pyopencv/pyopencvext/CascadeClassifier.pypp.cpp
pyopencv/pyopencvext/CascadeClassifier.pypp.hpp
pyopencv/pyopencvext/Complexd.pypp.cpp
pyopencv/pyopencvext/Complexd.pypp.hpp
pyopencv/pyopencvext/Complexf.pypp.cpp
pyopencv/pyopencvext/Complexf.pypp.hpp
pyopencv/pyopencvext/CompositeIndexParams.pypp.cpp
pyopencv/pyopencvext/CompositeIndexParams.pypp.hpp
pyopencv/pyopencvext/CvANN_MLP.pypp.cpp
pyopencv/pyopencvext/CvANN_MLP.pypp.hpp
pyopencv/pyopencvext/CvANN_MLP_TrainParams.pypp.cpp
pyopencv/pyopencvext/CvANN_MLP_TrainParams.pypp.hpp
pyopencv/pyopencvext/CvAdaptiveSkinDetector.pypp.cpp
pyopencv/pyopencvext/CvAdaptiveSkinDetector.pypp.hpp
pyopencv/pyopencvext/CvAffinePose.pypp.cpp
pyopencv/pyopencvext/CvAffinePose.pypp.hpp
pyopencv/pyopencvext/CvAttrList.pypp.cpp
pyopencv/pyopencvext/CvAttrList.pypp.hpp
pyopencv/pyopencvext/CvAvgComp.pypp.cpp
pyopencv/pyopencvext/CvAvgComp.pypp.hpp
pyopencv/pyopencvext/CvBlob.pypp.cpp
pyopencv/pyopencvext/CvBlob.pypp.hpp
pyopencv/pyopencvext/CvBlobSeq.pypp.cpp
pyopencv/pyopencvext/CvBlobSeq.pypp.hpp
pyopencv/pyopencvext/CvBlobTrack.pypp.cpp
pyopencv/pyopencvext/CvBlobTrack.pypp.hpp
pyopencv/pyopencvext/CvBlobTrackSeq.pypp.cpp
